vidai/__init__.py
vidai/client.py
vidai/config.py
vidai/exceptions.py
vidai/models.py
vidai/performance.py
vidai/structured_output.py
vidai/utils.py
vidai/providers/__init__.py
vidai/providers/anthropic.py
vidai/providers/base.py
vidai/providers/deepseek.py
vidai/providers/factory.py
vidai/providers/gemini.py
vidai/providers/groq.py
vidai/providers/openai.py
vidai/providers/strategies.py
vidai/providers/vidai_proxy.py
vidai/providers/vllm.py
vidaisdk-0.5.0.dist-info/METADATA
vidaisdk-0.5.0.dist-info/WHEEL
vidaisdk-0.5.0.dist-info/licenses/LICENSE
vidaisdk-0.5.0.dist-info/RECORD
