Metadata-Version: 2.4
Name: vidaisdk
Version: 0.5.0
Summary: Universal OpenAI-compatible Client with Structured Output Guarantees
Project-URL: Homepage, https://github.com/vidaiUK/vidaisdk
Project-URL: Documentation, https://github.com/vidaiUK/vidaisdk
Project-URL: Repository, https://github.com/vidaiUK/vidaisdk.git
Project-URL: Issues, https://github.com/vidaiUK/vidaisdk/issues
Author-email: Vidai Team <dev@vidai.ai>
License: Apache-2.0
License-File: LICENSE
Classifier: Development Status :: 4 - Beta
Classifier: Intended Audience :: Developers
Classifier: License :: OSI Approved :: Apache Software License
Classifier: Programming Language :: Python :: 3
Classifier: Programming Language :: Python :: 3.9
Classifier: Programming Language :: Python :: 3.10
Classifier: Programming Language :: Python :: 3.11
Classifier: Programming Language :: Python :: 3.12
Requires-Python: >=3.9
Requires-Dist: json-repair>=0.25.0
Requires-Dist: openai>=1.0.0
Requires-Dist: pydantic>=2.0.0
Provides-Extra: dev
Requires-Dist: black>=23.0.0; extra == 'dev'
Requires-Dist: mypy>=1.0.0; extra == 'dev'
Requires-Dist: pre-commit>=3.0.0; extra == 'dev'
Requires-Dist: pytest-asyncio>=0.21.0; extra == 'dev'
Requires-Dist: pytest-benchmark>=4.0.0; extra == 'dev'
Requires-Dist: pytest-cov>=4.0.0; extra == 'dev'
Requires-Dist: pytest>=7.0.0; extra == 'dev'
Requires-Dist: ruff>=0.1.0; extra == 'dev'
